{"day": "26JUL07", "series": [{"t": 1783436535, "pnl": 1.58, "roi": 0.7, "green": 52, "real": -3.97, "n": 21, "p5": -23.19, "p95": 12.81}, {"t": 1783436871, "pnl": 1.52, "roi": 0.6, "green": 51, "real": -3.97, "n": 21, "p5": -23.19, "p95": 12.81}, {"t": 1783437216, "pnl": 1.58, "roi": 0.7, "green": 52, "real": -3.97, "n": 21, "p5": -23.19, "p95": 12.81}, {"t": 1783437577, "pnl": 1.6, "roi": 0.7, "green": 52, "real": -3.97, "n": 22, "p5": -22.95, "p95": 13.05}, {"t": 1783437915, "pnl": 1.6, "roi": 0.7, "green": 52, "real": -3.97, "n": 22, "p5": -22.95, "p95": 13.05}, {"t": 1783438276, "pnl": 1.25, "roi": 0.5, "green": 51, "real": -3.97, "n": 22, "p5": -22.95, "p95": 13.05}, {"t": 1783438609, "pnl": 1.25, "roi": 0.5, "green": 51, "real": -3.97, "n": 22, "p5": -22.95, "p95": 13.05}, {"t": 1783438964, "pnl": 0.91, "roi": 0.4, "green": 49, "real": -3.97, "n": 22, "p5": -22.95, "p95": 13.05}, {"t": 1783439311, "pnl": 1.67, "roi": 0.7, "green": 52, "real": -3.97, "n": 22, "p5": -22.95, "p95": 13.05}, {"t": 1783439641, "pnl": 1.68, "roi": 0.7, "green": 52, "real": -3.97, "n": 22, "p5": -22.71, "p95": 13.29}, {"t": 1783440008, "pnl": 0.78, "roi": 0.3, "green": 49, "real": -3.97, "n": 22, "p5": -22.71, "p95": 13.29}, {"t": 1783440366, "pnl": 0.45, "roi": 0.2, "green": 48, "real": -3.97, "n": 23, "p5": -23.53, "p95": 13.47}, {"t": 1783440606, "pnl": 0.74, "roi": 0.3, "green": 49, "real": -3.97, "n": 23, "p5": -23.53, "p95": 13.47}, {"t": 1783440848, "pnl": 1.41, "roi": 0.6, "green": 51, "real": -3.97, "n": 23, "p5": -22.53, "p95": 13.47}, {"t": 1783441192, "pnl": 0.74, "roi": 0.3, "green": 50, "real": -3.63, "n": 17, "p5": -22.63, "p95": 13.37}, {"t": 1783441530, "pnl": 1.09, "roi": 0.4, "green": 51, "real": -3.63, "n": 18, "p5": -22.51, "p95": 13.49}, {"t": 1783441885, "pnl": 0.7, "roi": 0.3, "green": 50, "real": -3.63, "n": 18, "p5": -23.51, "p95": 13.49}, {"t": 1783442220, "pnl": 1.35, "roi": 0.6, "green": 52, "real": -3.63, "n": 18, "p5": -22.51, "p95": 13.49}, {"t": 1783442583, "pnl": 1.74, "roi": 0.7, "green": 53, "real": -3.63, "n": 18, "p5": -22.51, "p95": 13.49}, {"t": 1783442911, "pnl": 1.78, "roi": 0.7, "green": 53, "real": -3.63, "n": 18, "p5": -22.51, "p95": 13.49}, {"t": 1783443261, "pnl": 1.14, "roi": 0.5, "green": 51, "real": -3.63, "n": 18, "p5": -22.51, "p95": 13.49}, {"t": 1783443616, "pnl": 3.14, "roi": 1.3, "green": 57, "real": -3.63, "n": 18, "p5": -21.51, "p95": 13.49}, {"t": 1783443980, "pnl": 3.1, "roi": 1.3, "green": 57, "real": -3.63, "n": 18, "p5": -21.51, "p95": 13.49}, {"t": 1783444326, "pnl": 1.87, "roi": 0.8, "green": 52, "real": -3.63, "n": 18, "p5": -22.13, "p95": 13.87}, {"t": 1783444687, "pnl": 1.62, "roi": 0.7, "green": 52, "real": -3.63, "n": 18, "p5": -22.13, "p95": 13.87}, {"t": 1783445044, "pnl": 1.85, "roi": 0.7, "green": 52, "real": -3.63, "n": 18, "p5": -22.13, "p95": 13.87}, {"t": 1783445380, "pnl": 1.85, "roi": 0.7, "green": 52, "real": -3.63, "n": 18, "p5": -22.13, "p95": 13.87}, {"t": 1783445748, "pnl": 2.74, "roi": 1.1, "green": 56, "real": -3.63, "n": 18, "p5": -22.13, "p95": 13.87}, {"t": 1783446110, "pnl": 1.97, "roi": 0.8, "green": 53, "real": -3.63, "n": 18, "p5": -22.13, "p95": 13.87}, {"t": 1783446468, "pnl": 1.99, "roi": 0.8, "green": 53, "real": -3.63, "n": 18, "p5": -22.13, "p95": 13.87}, {"t": 1783446836, "pnl": 1.99, "roi": 0.8, "green": 53, "real": -3.63, "n": 18, "p5": -22.13, "p95": 13.87}, {"t": 1783447164, "pnl": 1.21, "roi": 0.5, "green": 51, "real": -3.63, "n": 18, "p5": -22.13, "p95": 13.87}, {"t": 1783447533, "pnl": 2.42, "roi": 0.9, "green": 56, "real": -3.63, "n": 19, "p5": -21.64, "p95": 14.36}, {"t": 1783447890, "pnl": 2.21, "roi": 0.9, "green": 56, "real": -3.63, "n": 19, "p5": -21.64, "p95": 14.36}, {"t": 1783448260, "pnl": 2.04, "roi": 0.8, "green": 54, "real": -3.63, "n": 19, "p5": -21.64, "p95": 14.36}, {"t": 1783448629, "pnl": 2.36, "roi": 0.9, "green": 55, "real": -3.63, "n": 19, "p5": -21.64, "p95": 14.36}, {"t": 1783448965, "pnl": 0.42, "roi": 0.2, "green": 49, "real": -3.63, "n": 19, "p5": -25.64, "p95": 14.36}, {"t": 1783449296, "pnl": 1.8, "roi": 0.7, "green": 52, "real": -3.63, "n": 19, "p5": -21.64, "p95": 14.36}, {"t": 1783449663, "pnl": 0.98, "roi": 0.4, "green": 49, "real": -3.63, "n": 19, "p5": -24.64, "p95": 14.36}, {"t": 1783450024, "pnl": 0.12, "roi": 0.0, "green": 47, "real": -3.63, "n": 20, "p5": -26.49, "p95": 14.51}, {"t": 1783450390, "pnl": 1.58, "roi": 0.6, "green": 51, "real": -3.63, "n": 20, "p5": -23.49, "p95": 14.51}, {"t": 1783450749, "pnl": 2.3, "roi": 0.9, "green": 54, "real": -3.63, "n": 20, "p5": -21.49, "p95": 14.51}, {"t": 1783451099, "pnl": 1.02, "roi": 0.4, "green": 50, "real": -3.63, "n": 20, "p5": -24.49, "p95": 14.51}, {"t": 1783451456, "pnl": 1.24, "roi": 0.5, "green": 50, "real": -3.63, "n": 20, "p5": -24.49, "p95": 14.51}, {"t": 1783451817, "pnl": 1.63, "roi": 0.6, "green": 52, "real": -3.63, "n": 20, "p5": -23.49, "p95": 14.51}, {"t": 1783452172, "pnl": 0.9, "roi": 0.3, "green": 50, "real": -3.63, "n": 20, "p5": -25.49, "p95": 14.51}, {"t": 1783452545, "pnl": 0.4, "roi": 0.2, "green": 49, "real": -3.63, "n": 20, "p5": -25.49, "p95": 14.51}, {"t": 1783452870, "pnl": 0.43, "roi": 0.2, "green": 49, "real": -3.63, "n": 21, "p5": -25.44, "p95": 14.56}, {"t": 1783453161, "pnl": 1.3, "roi": 0.5, "green": 52, "real": -3.63, "n": 21, "p5": -24.44, "p95": 14.56}, {"t": 1783453559, "pnl": 2.69, "roi": 1.0, "green": 56, "real": -3.63, "n": 21, "p5": -21.44, "p95": 14.56}, {"t": 1783453912, "pnl": 2.69, "roi": 1.0, "green": 56, "real": -3.63, "n": 21, "p5": -21.44, "p95": 14.56}, {"t": 1783454271, "pnl": 2.69, "roi": 1.0, "green": 56, "real": -3.63, "n": 21, "p5": -21.44, "p95": 14.56}, {"t": 1783454626, "pnl": 4.37, "roi": 1.7, "green": 63, "real": -3.63, "n": 21, "p5": -19.44, "p95": 14.56}, {"t": 1783454995, "pnl": 4.91, "roi": 1.9, "green": 65, "real": -3.63, "n": 21, "p5": -18.44, "p95": 14.56}, {"t": 1783455371, "pnl": 4.91, "roi": 1.9, "green": 65, "real": -3.63, "n": 21, "p5": -18.44, "p95": 14.56}, {"t": 1783455727, "pnl": 4.8, "roi": 1.8, "green": 65, "real": -3.63, "n": 23, "p5": -18.21, "p95": 14.79}, {"t": 1783456062, "pnl": 4.61, "roi": 1.7, "green": 64, "real": -3.63, "n": 23, "p5": -18.21, "p95": 14.79}, {"t": 1783456422, "pnl": 4.82, "roi": 1.8, "green": 65, "real": -3.63, "n": 23, "p5": -18.21, "p95": 14.79}, {"t": 1783456731, "pnl": 4.8, "roi": 1.8, "green": 65, "real": -3.63, "n": 23, "p5": -18.21, "p95": 14.79}, {"t": 1783457082, "pnl": 4.99, "roi": 1.9, "green": 65, "real": -3.63, "n": 23, "p5": -18.21, "p95": 14.79}, {"t": 1783457439, "pnl": 4.99, "roi": 1.9, "green": 65, "real": -3.63, "n": 23, "p5": -18.21, "p95": 14.79}, {"t": 1783457799, "pnl": 5.06, "roi": 1.9, "green": 69, "real": -3.63, "n": 24, "p5": -17.93, "p95": 15.07}, {"t": 1783458162, "pnl": 2.69, "roi": 1.0, "green": 59, "real": -2.87, "n": 24, "p5": -21.39, "p95": 14.61}, {"t": 1783458498, "pnl": 3.16, "roi": 1.2, "green": 60, "real": -2.87, "n": 25, "p5": -21.09, "p95": 14.91}, {"t": 1783458864, "pnl": 3.01, "roi": 1.1, "green": 62, "real": -2.87, "n": 26, "p5": -20.79, "p95": 15.21}, {"t": 1783459225, "pnl": 3.38, "roi": 1.3, "green": 63, "real": -2.87, "n": 26, "p5": -20.79, "p95": 15.21}, {"t": 1783459575, "pnl": 3.67, "roi": 1.4, "green": 65, "real": -2.87, "n": 26, "p5": -19.79, "p95": 15.21}]}