{"day": "26JUL17", "series": [{"t": 1784286541, "pnl": 3.67, "roi": 2.9, "green": 83, "real": -20.82, "n": 15, "p5": -11.04, "p95": 6.96}, {"t": 1784286863, "pnl": 3.38, "roi": 2.7, "green": 80, "real": -20.82, "n": 15, "p5": -11.04, "p95": 6.96}, {"t": 1784287184, "pnl": 3.38, "roi": 2.4, "green": 78, "real": -20.82, "n": 16, "p5": -10.62, "p95": 7.38}, {"t": 1784287528, "pnl": 3.38, "roi": 2.4, "green": 78, "real": -20.82, "n": 16, "p5": -10.62, "p95": 7.38}, {"t": 1784287847, "pnl": 3.38, "roi": 2.4, "green": 78, "real": -20.82, "n": 16, "p5": -10.62, "p95": 7.38}, {"t": 1784288166, "pnl": 3.42, "roi": 2.4, "green": 78, "real": -20.82, "n": 16, "p5": -10.62, "p95": 7.38}, {"t": 1784288508, "pnl": 3.42, "roi": 2.4, "green": 78, "real": -20.82, "n": 16, "p5": -10.62, "p95": 7.38}, {"t": 1784288828, "pnl": 3.42, "roi": 2.4, "green": 78, "real": -20.82, "n": 16, "p5": -10.62, "p95": 7.38}, {"t": 1784289166, "pnl": 3.42, "roi": 2.4, "green": 78, "real": -20.82, "n": 16, "p5": -10.62, "p95": 7.38}, {"t": 1784289499, "pnl": 3.67, "roi": 2.6, "green": 79, "real": -20.82, "n": 16, "p5": -10.62, "p95": 7.38}, {"t": 1784289820, "pnl": 2.59, "roi": 2.4, "green": 70, "real": -19.38, "n": 14, "p5": -12.06, "p95": 5.94}, {"t": 1784290158, "pnl": 3.11, "roi": 2.9, "green": 75, "real": -19.38, "n": 14, "p5": -10.06, "p95": 5.94}, {"t": 1784290485, "pnl": 3.06, "roi": 2.9, "green": 74, "real": -19.38, "n": 14, "p5": -10.06, "p95": 5.94}, {"t": 1784290804, "pnl": 3.37, "roi": 3.2, "green": 76, "real": -19.38, "n": 14, "p5": -9.06, "p95": 5.94}, {"t": 1784291145, "pnl": 3.38, "roi": 3.0, "green": 86, "real": -19.38, "n": 15, "p5": -8.64, "p95": 6.36}, {"t": 1784291464, "pnl": 3.59, "roi": 2.9, "green": 83, "real": -19.38, "n": 16, "p5": -11.04, "p95": 6.96}, {"t": 1784291783, "pnl": 3.34, "roi": 2.7, "green": 83, "real": -19.38, "n": 16, "p5": -11.04, "p95": 6.96}, {"t": 1784292123, "pnl": 4.07, "roi": 3.0, "green": 81, "real": -19.38, "n": 17, "p5": -10.14, "p95": 7.86}, {"t": 1784292443, "pnl": 4.07, "roi": 3.0, "green": 81, "real": -19.38, "n": 17, "p5": -10.14, "p95": 7.86}, {"t": 1784292767, "pnl": 3.82, "roi": 2.8, "green": 80, "real": -19.38, "n": 17, "p5": -10.14, "p95": 7.86}, {"t": 1784293109, "pnl": 4.17, "roi": 3.0, "green": 80, "real": -19.38, "n": 17, "p5": -10.14, "p95": 7.86}, {"t": 1784293429, "pnl": 4.32, "roi": 3.1, "green": 82, "real": -19.38, "n": 17, "p5": -10.14, "p95": 7.86}, {"t": 1784293762, "pnl": 4.11, "roi": 3.0, "green": 81, "real": -19.38, "n": 17, "p5": -10.14, "p95": 7.86}, {"t": 1784294091, "pnl": 3.9, "roi": 2.8, "green": 80, "real": -19.38, "n": 17, "p5": -10.14, "p95": 7.86}, {"t": 1784294411, "pnl": 3.9, "roi": 2.8, "green": 80, "real": -19.38, "n": 17, "p5": -10.14, "p95": 7.86}, {"t": 1784294747, "pnl": 3.8, "roi": 2.8, "green": 79, "real": -19.38, "n": 17, "p5": -10.14, "p95": 7.86}]}